restrict_imports/__init__.py
restrict_imports/checker.py
flake8_restrict_imports-0.1.1.dist-info/LICENSE
flake8_restrict_imports-0.1.1.dist-info/METADATA
flake8_restrict_imports-0.1.1.dist-info/WHEEL
flake8_restrict_imports-0.1.1.dist-info/entry_points.txt
flake8_restrict_imports-0.1.1.dist-info/top_level.txt
flake8_restrict_imports-0.1.1.dist-info/RECORD
